langsearch/__init__.py
langsearch/langsearch.py
langsearch_mcp-0.1.1.dist-info/METADATA
langsearch_mcp-0.1.1.dist-info/WHEEL
langsearch_mcp-0.1.1.dist-info/entry_points.txt
langsearch_mcp-0.1.1.dist-info/RECORD
